{
    "whats-new":[
        {
            "date":"2023/03/09",
            "message":"ボーマス51に参加申し込みしました。 "
        },
        {
            "date":"2023/03/14",
            "message":"HPを更新しました"
        }
    ],
    "members":[
        {
            "name": "ななみつき",  
            "youtubeID": "UC7MR9RVYEZzeEohsAaoz3yA",
            "niconicoID": "50002604",

            "twitterID": "nanamitsuki_73",
            "instagramID": "",
            "tiktokID":"nanamitsuki_73",

            "comment": "のんびり曲を作るよ。",
            "imgLink":"https://pbs.twimg.com/profile_images/1343228076621090816/yoWO3R4l_400x400.jpg"
        },
        {
            "name": "Urban"
        },
        {
            "name":"光る山羊"
        }
    ]
}
